dpkgs3-0.0.1.dev3.dist-info/METADATA
dpkgs3-0.0.1.dev3.dist-info/WHEEL
dpkgs3-0.0.1.dev3.dist-info/entry_points.txt
dpkgs3/.mypy_cache/.gitignore
dpkgs3/.mypy_cache/3.8/@plugins_snapshot.json
dpkgs3/.mypy_cache/3.8/_ast.data.json
dpkgs3/.mypy_cache/3.8/_ast.meta.json
dpkgs3/.mypy_cache/3.8/_codecs.data.json
dpkgs3/.mypy_cache/3.8/_codecs.meta.json
dpkgs3/.mypy_cache/3.8/_collections_abc.data.json
dpkgs3/.mypy_cache/3.8/_collections_abc.meta.json
dpkgs3/.mypy_cache/3.8/_typeshed/__init__.data.json
dpkgs3/.mypy_cache/3.8/_typeshed/__init__.meta.json
dpkgs3/.mypy_cache/3.8/abc.data.json
dpkgs3/.mypy_cache/3.8/abc.meta.json
dpkgs3/.mypy_cache/3.8/builtins.data.json
dpkgs3/.mypy_cache/3.8/builtins.meta.json
dpkgs3/.mypy_cache/3.8/codecs.data.json
dpkgs3/.mypy_cache/3.8/codecs.meta.json
dpkgs3/.mypy_cache/3.8/collections/__init__.data.json
dpkgs3/.mypy_cache/3.8/collections/__init__.meta.json
dpkgs3/.mypy_cache/3.8/collections/abc.data.json
dpkgs3/.mypy_cache/3.8/collections/abc.meta.json
dpkgs3/.mypy_cache/3.8/contextlib.data.json
dpkgs3/.mypy_cache/3.8/contextlib.meta.json
dpkgs3/.mypy_cache/3.8/dataclasses.data.json
dpkgs3/.mypy_cache/3.8/dataclasses.meta.json
dpkgs3/.mypy_cache/3.8/dpkg_s3/__init__.data.json
dpkgs3/.mypy_cache/3.8/dpkg_s3/__init__.meta.json
dpkgs3/.mypy_cache/3.8/dpkg_s3/package.data.json
dpkgs3/.mypy_cache/3.8/dpkg_s3/package.meta.json
dpkgs3/.mypy_cache/3.8/dpkg_s3/release.data.json
dpkgs3/.mypy_cache/3.8/dpkg_s3/release.meta.json
dpkgs3/.mypy_cache/3.8/dpkg_s3/s3.data.json
dpkgs3/.mypy_cache/3.8/dpkg_s3/s3.meta.json
dpkgs3/.mypy_cache/3.8/email/__init__.data.json
dpkgs3/.mypy_cache/3.8/email/__init__.meta.json
dpkgs3/.mypy_cache/3.8/email/charset.data.json
dpkgs3/.mypy_cache/3.8/email/charset.meta.json
dpkgs3/.mypy_cache/3.8/email/contentmanager.data.json
dpkgs3/.mypy_cache/3.8/email/contentmanager.meta.json
dpkgs3/.mypy_cache/3.8/email/errors.data.json
dpkgs3/.mypy_cache/3.8/email/errors.meta.json
dpkgs3/.mypy_cache/3.8/email/header.data.json
dpkgs3/.mypy_cache/3.8/email/header.meta.json
dpkgs3/.mypy_cache/3.8/email/message.data.json
dpkgs3-0.0.1.dev3.dist-info/RECORD
